setup.cfg
setup.py
rlstm/__init__.py
rlstm/_models_util.py
rlstm/autograd_util.py
rlstm/common_util.py
rlstm/create_toy_data.py
rlstm/cross_validation.py
rlstm/debug_util.py
rlstm/models_util.py
rlstm/nn_util.py
rlstm/optimize.py
rlstm/pipe_save.py
rlstm/pipeline.py
rlstm/scores.py
rlstm/weights_parser.py
rlstm.egg-info/PKG-INFO
rlstm.egg-info/SOURCES.txt
rlstm.egg-info/dependency_links.txt
rlstm.egg-info/not-zip-safe
rlstm.egg-info/requires.txt
rlstm.egg-info/top_level.txt
rlstm/compression/__init__.py
rlstm/compression/munge.py
rlstm/compression/munge_example.py
rlstm/compression/workspace.py
rlstm/datasets/X_test.npy
rlstm/datasets/X_train.npy
rlstm/datasets/X_valid.npy
rlstm/datasets/__init__.py
rlstm/datasets/__init__.pyc
rlstm/datasets/fcpt_test.npy
rlstm/datasets/fcpt_train.npy
rlstm/datasets/fcpt_valid.npy
rlstm/datasets/obs_set.npy
rlstm/datasets/out_set.npy
rlstm/datasets/param_set.pkl
rlstm/datasets/y_test.npy
rlstm/datasets/y_train.npy
rlstm/datasets/y_valid.npy
rlstm/distillation/__init__.py
rlstm/distillation/grudistill.py
rlstm/distillation/workspace.py
rlstm/emission_models/__init__.py
rlstm/emission_models/bernoulli_multivariate.py
rlstm/emission_models/diagonal_gaussian_multivariate.py
rlstm/emission_models/test_bernoulli_multivariate.py
rlstm/emission_models/test_diagonal_gaussian_multivariate.py
rlstm/interpret/__init__.py
rlstm/interpret/rnn_tree.py
rlstm/interpret/rnn_weight_map.py
rlstm/models/__init__.py
rlstm/models/gru.py
rlstm/models/gruhmm.py
rlstm/models/hmm.py
rlstm/models/hmm_test.py
rlstm/models/lr.py
rlstm/models/mlp.py
rlstm/sample/__init__.py
rlstm/sample/sample_timeseries.py
rlstm/tests/__init__.py
rlstm/tests/test_marmalade.py
rlstm/tests/test_sparsearray.py
rlstm/tests/test_subsample.py
rlstm/tests/test_vectorization.py