Metadata-Version: 1.1
Name: rlstm
Version: 0.2.39
Summary: Pipeline tool for machine learning models.
Home-page: https://github.com/dtak/interpretable-models
Author: Mike Wu
Author-email: me@mikewuis.me
License: UNKNOWN
Download-URL: https://github.com/dtak/interpretable-models/tarball/0.1.0
Keywords: generative,interpretable,hmm,lstm,residual
Platform: UNKNOWN
